mfd_serial/__init__.py
mfd_serial/serial.py
mfd_serial-1.7.0.dist-info/licenses/AUTHORS.md
mfd_serial-1.7.0.dist-info/licenses/LICENSE.md
mfd_serial-1.7.0.dist-info/METADATA
mfd_serial-1.7.0.dist-info/WHEEL
mfd_serial-1.7.0.dist-info/top_level.txt
mfd_serial-1.7.0.dist-info/RECORD
