Metadata-Version: 2.4
Name: mfd-serial
Version: 1.7.0
Summary: Module for handling communication via serial port like Universal asynchronous receiver-transmitter (UART)
Project-URL: Homepage, https://github.com/intel/mfd
Project-URL: Repository, https://github.com/intel/mfd-serial
Project-URL: Issues, https://github.com/intel/mfd-serial/issues
Project-URL: Changelog, https://github.com/intel/mfd-serial/blob/main/CHANGELOG.md
Requires-Python: <3.14,>=3.10
License-File: LICENSE.md
License-File: AUTHORS.md
Requires-Dist: pyserial==3.5
Requires-Dist: mfd-common-libs>=1.11.0
Dynamic: license-file
